user_auth_validator/__init__.py
user_auth_validator/validators.py
user_auth_validator-0.1.0.dist-info/LICENSE
user_auth_validator-0.1.0.dist-info/METADATA
user_auth_validator-0.1.0.dist-info/WHEEL
user_auth_validator-0.1.0.dist-info/top_level.txt
user_auth_validator-0.1.0.dist-info/RECORD
