Metadata-Version: 2.1
Name: user-auth-validator
Version: 0.1.0
Summary: A library for validating usernames, emails, and passwords.
Home-page: https://github.com/yourusername/user-auth-validator
Author: Your Name
Author-email: your.email@example.com
Classifier: Programming Language :: Python :: 3
Classifier: License :: OSI Approved :: MIT License
Classifier: Operating System :: OS Independent
Requires-Python: >=3.6
License-File: LICENSE
